topsis/Aryan-102213016.py
topsis/__init__.py
Topsis_Aryan_102213016-1.0.0.dist-info/LICENSE
Topsis_Aryan_102213016-1.0.0.dist-info/METADATA
Topsis_Aryan_102213016-1.0.0.dist-info/WHEEL
Topsis_Aryan_102213016-1.0.0.dist-info/entry_points.txt
Topsis_Aryan_102213016-1.0.0.dist-info/top_level.txt
Topsis_Aryan_102213016-1.0.0.dist-info/RECORD
