Metadata-Version: 2.2
Name: Topsis-Aryan-102213016
Version: 1.0.0
Summary: A Python package for TOPSIS-based decision-making.
Home-page: https://github.com/aryanbakshi04/Topsis_Aryan_Bakshi_102213016
Author: Aryan Bakshi
Author-email: bakshiaryan01@gmail.com
Classifier: Programming Language :: Python :: 3
Classifier: License :: OSI Approved :: MIT License
Classifier: Operating System :: OS Independent
Requires-Python: >=3.6
License-File: LICENSE
Requires-Dist: pandas
Requires-Dist: numpy
Dynamic: author
Dynamic: author-email
Dynamic: classifier
Dynamic: description
Dynamic: description-content-type
Dynamic: home-page
Dynamic: requires-dist
Dynamic: requires-python
Dynamic: summary
